cas/__init__.py
cas/__main__.py
cas/abc_cas_converter.py
cas/accession/__init__.py
cas/accession/base_accession_manager.py
cas/accession/hash_accession_manager.py
cas/accession/incremental_accession_manager.py
cas/accession/mapped_accession_manager.py
cas/add_author_annotations.py
cas/anndata_conversion.py
cas/anndata_splitter.py
cas/anndata_to_cas.py
cas/cas_splitter.py
cas/cas_to_rdf.py
cas/cxg_utils.py
cas/dataset_retrieval/__init__.py
cas/dataset_retrieval/cxg_downloader.py
cas/dataset_retrieval/dataset_retriever.py
cas/dataset_retrieval/http_downloader.py
cas/dataset_retrieval/s3_downloader.py
cas/file_utils.py
cas/flatten_data_to_anndata.py
cas/flatten_data_to_tables.py
cas/ingest/__init__.py
cas/ingest/config_schema.yaml
cas/ingest/config_validator.py
cas/ingest/ingest_user_table.py
cas/matrix_file/__init__.py
cas/matrix_file/base_resolver.py
cas/matrix_file/cxg_resolver.py
cas/matrix_file/resolver.py
cas/model.py
cas/populate_cell_ids.py
cas/reports.py
cas/spreadsheet_to_cas.py
cas/utils/__init__.py
cas/utils/conversion_utils.py
cas/utils/validation_utils.py
cas/validate.py
cas_tools-1.1.8.dist-info/METADATA
cas_tools-1.1.8.dist-info/WHEEL
cas_tools-1.1.8.dist-info/entry_points.txt
cas_tools-1.1.8.dist-info/RECORD
