Metadata-Version: 2.3
Name: cas-tools
Version: 1.1.8
Summary: Cell Annotation Schema tools.
License: Apache-2.0 license
Author: Huseyin Kir
Author-email: hk9@sanger.ac.uk
Requires-Python: >=3.10,<4.0
Classifier: License :: Other/Proprietary License
Classifier: Programming Language :: Python :: 3
Classifier: Programming Language :: Python :: 3.10
Classifier: Programming Language :: Python :: 3.11
Classifier: Programming Language :: Python :: 3.12
Classifier: Programming Language :: Python :: 3.13
Provides-Extra: docs
Requires-Dist: anndata (==0.10.5)
Requires-Dist: cap-anndata (>=0.3.0,<0.4.0)
Requires-Dist: cas-linkml (==0.0.15)
Requires-Dist: cell-annotation-schema (==1.1.0)
Requires-Dist: cellxgene-census (==1.16.0) ; python_version >= "3.10" and python_version < "3.13"
Requires-Dist: dataclasses-json (==0.6.4)
Requires-Dist: deepmerge (==1.1.0)
Requires-Dist: defusedxml (==0.7.1)
Requires-Dist: h5py (==3.10.0)
Requires-Dist: jsonschema (==4.4.0)
Requires-Dist: linkml (==1.7.8)
Requires-Dist: marshmallow (==3.21.1)
Requires-Dist: numpy (==1.26.4)
Requires-Dist: oaklib (==0.6.4)
Requires-Dist: openpyxl (==3.1.2)
Requires-Dist: ordered-set (==4.1.0)
Requires-Dist: pandas (==2.2.1)
Requires-Dist: psycopg2-binary (==2.9.5)
Requires-Dist: python-dateutil (==2.9.0)
Requires-Dist: rdflib (==7.0.0)
Requires-Dist: requests (==2.32.3)
Requires-Dist: ruamel-yaml (==0.18.6)
Requires-Dist: schema-automator (==0.5.1)
Requires-Dist: urllib3 (<2)
Project-URL: Homepage, https://github.com/cellannotation/cas-tools
Project-URL: Repository, https://github.com/cellannotation/cas-tools
